{
    "d8772c89d210fb4d803218e68750aeca": {
        "original_text": "ん？",
        "translated_text": "Hm?"
    },
    "40bf6f13a5f87cac82aeccac80ca4f0c": {
        "original_text": "とあちゃんさ",
        "translated_text": "Toa-chan."
    },
    "09587b112cba65cad1a5c17792bcc5e0": {
        "original_text": "一緒に暮らそうか",
        "translated_text": "Haruskah kita hidup bersama?"
    },
    "34b659d15a221d91b0de4a4937fa514d": {
        "original_text": "ママ帰ってこないなら俺と暮らそうよ",
        "translated_text": "Jika kamu tidak pulang, Bu, datang dan tinggal bersamaku."
    },
    "433d7e2e6cb1f9ab2d62de3ca6f12b70": {
        "original_text": "え。",
        "translated_text": "Eh."
    },
    "8d4116ff3e62fc39c7bd2118029ff8fa": {
        "original_text": "ええっええ～",
        "translated_text": "Ehhhhhhh!"
    },
    "dd82771a14e658d13790d57d697bd87c": {
        "original_text": "んっ",
        "translated_text": "hmm"
    },
    "7cd6d68f3006955f55bc78e62c39beff": {
        "original_text": "それ、やだ",
        "translated_text": "Oh, tidak."
    },
    "98fbb5eb86978a5020dc0d7f3d27b66a": {
        "original_text": "気持ちいいってことだよ",
        "translated_text": "Maksud saya, rasanya menyenangkan."
    },
    "0b6cc88b6b591cb1688f6fa49910f7d6": {
        "original_text": "んう",
        "translated_text": "turun"
    },
    "c791dc130071e2a23c0c31567918f093": {
        "original_text": "んっ",
        "translated_text": "hmm"
    }
}